{
  "companies": [
    {
      "_id": "69873a5a1d893c740340fcba",
      "name": "Demo Company",
      "currency": "INR",
      "planId": "69873a5a1d893c740340fcb7",
      "subscriptionStatus": "active",
      "featureFlags": {
        "employees": true,
        "module_employees": true
      },
      "invoiceEditPassword": null,
      "maxDevices": 5,
      "apiKey": "sk_demo_1770469978836",
      "devices": [],
      "createdAt": "2026-02-07T13:12:58.839Z",
      "__v": 0,
      "subscriptionEndsAt": "2027-02-11T15:16:04.461Z"
    }
  ],
  "employees": [
    {
      "freeLeavesPerMonth": 1,
      "workingDaysPerWeek": 6,
      "_id": "6989b60ce30e7e5e38886bd3",
      "companyId": "69873a5a1d893c740340fcba",
      "firstName": "swej",
      "lastName": "Patel",
      "email": "pswej@gmail.com",
      "phone": "user@company.com",
      "password": "$2b$10$l74ZCg5Kd76zS62NuiGcX./g8OiUbVIBvJiIkgt8M74ThNdv78pGK",
      "category": "General",
      "position": "normal",
      "department": "Management",
      "salary": 20000,
      "status": "Active",
      "dateHired": "2026-02-09T10:25:16.034Z",
      "isDeleted": true,
      "createdAt": "2026-02-09T10:25:16.035Z",
      "updatedAt": "2026-02-09T10:40:24.585Z",
      "__v": 0,
      "salaryHistory": []
    },
    {
      "freeLeavesPerMonth": 1,
      "workingDaysPerWeek": 6,
      "_id": "6989b62ce30e7e5e38886bd8",
      "companyId": "69873a5a1d893c740340fcba",
      "firstName": "swej",
      "lastName": "Patel",
      "email": "pswej11@gmail.com",
      "phone": "7861971504",
      "password": "$2b$10$gNPZ2b71BLsPTwawhTKhQOIXqfuUpXmA5VPD71Zp4mYjCifs6kPNC",
      "category": "General",
      "position": "normal",
      "department": "Management",
      "salary": 20000,
      "status": "Active",
      "dateHired": "2026-02-09T10:25:48.500Z",
      "isDeleted": true,
      "createdAt": "2026-02-09T10:25:48.501Z",
      "updatedAt": "2026-02-09T10:40:21.927Z",
      "__v": 0,
      "salaryHistory": []
    },
    {
      "freeLeavesPerMonth": 1,
      "workingDaysPerWeek": 6,
      "_id": "6989e898b58fc7dcd227d170",
      "companyId": "69873a5a1d893c740340fcba",
      "firstName": "swej",
      "lastName": "Patel",
      "email": "pswej9@gmail.com",
      "phone": "7861971503",
      "password": "$2b$10$gHcHYQOlgOMFB6MOvMDP/e9P.Ichc0e7g9pao7QrP66r1QWzmAFjO",
      "category": "General",
      "position": "normal",
      "department": "Management",
      "salary": 20000,
      "status": "Active",
      "dateHired": "2026-02-09T14:00:56.703Z",
      "isDeleted": true,
      "createdAt": "2026-02-09T14:00:56.704Z",
      "updatedAt": "2026-02-09T14:01:57.924Z",
      "__v": 0,
      "salaryHistory": []
    },
    {
      "freeLeavesPerMonth": 1,
      "workingDaysPerWeek": 6,
      "_id": "6989ea45b58fc7dcd227d183",
      "companyId": "69873a5a1d893c740340fcba",
      "firstName": "Test",
      "lastName": "User",
      "email": "test.employee.1770646085402@example.com",
      "phone": "+11770646085402",
      "password": "$2b$10$nzPrdqEL6WdhzHz5yg1N3uZ36ElhhiXbDPll55jn0HxsNoOHecs9m",
      "category": "General",
      "position": "Developer",
      "department": "Engineering",
      "salary": 50000,
      "status": "Active",
      "dateHired": "2026-02-09T14:08:05.408Z",
      "isDeleted": true,
      "createdAt": "2026-02-09T14:08:05.607Z",
      "updatedAt": "2026-02-09T14:08:05.680Z",
      "__v": 0,
      "salaryHistory": []
    },
    {
      "freeLeavesPerMonth": 1,
      "workingDaysPerWeek": 6,
      "_id": "6989ea8501086ad882a11315",
      "companyId": "69873a5a1d893c740340fcba",
      "firstName": "Test",
      "lastName": "User",
      "email": "test.employee.1770646149475@example.com-deleted-1770646149832",
      "phone": "+11770646149475-deleted-1770646149832",
      "password": "$2b$10$hRqMtf/vIKO75i5FzshH1eJXlxd9kjJ0iILKFowC0JkS7S4SWdc7i",
      "category": "General",
      "position": "Developer",
      "department": "Engineering",
      "salary": 50000,
      "status": "Terminated",
      "dateHired": "2026-02-09T14:09:09.480Z",
      "isDeleted": true,
      "createdAt": "2026-02-09T14:09:09.654Z",
      "updatedAt": "2026-02-09T14:09:09.833Z",
      "__v": 0,
      "salaryHistory": []
    },
    {
      "_id": "6989ea8501086ad882a11319",
      "companyId": "69873a5a1d893c740340fcba",
      "firstName": "Test",
      "lastName": "User 2",
      "email": "test.employee.1770646149475@example.com",
      "phone": "9876543214",
      "password": "$2b$10$3GhdDuVZS5XoA8/wKaSCNeJXejzlKbo2ECiELisbvQb1ww.upfS0e",
      "category": "General",
      "position": "Developer",
      "department": "Engineering",
      "salary": 50000,
      "status": "Active",
      "dateHired": "2026-02-09T14:09:09.902Z",
      "isDeleted": false,
      "createdAt": "2026-02-09T14:09:09.985Z",
      "updatedAt": "2026-02-09T15:40:29.387Z",
      "__v": 1,
      "freeLeavesPerMonth": 1,
      "workingDaysPerWeek": 6,
      "salaryHistory": []
    },
    {
      "freeLeavesPerMonth": 1,
      "workingDaysPerWeek": 6,
      "_id": "6989eaf0b58fc7dcd227d188",
      "companyId": "69873a5a1d893c740340fcba",
      "firstName": "Demo",
      "lastName": "User 3682",
      "email": "demo.employee.3682@example.com",
      "phone": "9876543682",
      "password": "$2b$10$xhPIOEHTQAhK67XOVL18fuB5LjKO1g.5ekv6AH6EyQKMZ9DoveObi",
      "category": "General",
      "position": "Tester",
      "department": "QA",
      "salary": 60000,
      "status": "Active",
      "dateHired": "2026-02-09T14:10:56.199Z",
      "isDeleted": false,
      "createdAt": "2026-02-09T14:10:56.328Z",
      "updatedAt": "2026-02-09T14:10:56.328Z",
      "__v": 0,
      "salaryHistory": []
    },
    {
      "_id": "6989eb9fb58fc7dcd227d18c",
      "companyId": "69873a5a1d893c740340fcba",
      "firstName": "Demo",
      "lastName": "User 4737",
      "email": "demo.employee.4737@example.com",
      "phone": "+919876543214",
      "password": "$2b$10$WQeh/ZzTmpwcfCoj.GNNueD7v.JPuCgjT8W1X.VWJmv/xDxUSXBgi",
      "category": "General",
      "position": "Tester",
      "department": "QA",
      "salary": 60000,
      "status": "Active",
      "dateHired": "2026-02-09T14:13:51.832Z",
      "isDeleted": false,
      "createdAt": "2026-02-09T14:13:51.983Z",
      "updatedAt": "2026-02-09T15:40:29.565Z",
      "__v": 1,
      "freeLeavesPerMonth": 1,
      "workingDaysPerWeek": 6,
      "salaryHistory": []
    },
    {
      "_id": "6989fb2ce22141062a8df688",
      "companyId": "69873a5a1d893c740340fcba",
      "firstName": "Rahul",
      "lastName": "Sharma",
      "email": "rahul.sharma@example.com",
      "phone": "9876543210",
      "password": "$2b$10$txs2kNES7ZyVQ5SdMB617.KvnDJgJ88Bl56YUSJyv0dfAgfc./2xm",
      "category": "General",
      "position": "Senior Developer",
      "department": "Engineering",
      "salary": 1200000,
      "freeLeavesPerMonth": 1,
      "workingDaysPerWeek": 5,
      "status": "Active",
      "isDeleted": false,
      "salaryHistory": [],
      "dateHired": "2026-02-09T15:20:12.975Z",
      "createdAt": "2026-02-09T15:20:12.979Z",
      "updatedAt": "2026-02-09T15:40:29.702Z",
      "__v": 0
    },
    {
      "_id": "6989fb2de22141062a8df68b",
      "companyId": "69873a5a1d893c740340fcba",
      "firstName": "Priya",
      "lastName": "Verma",
      "email": "priya.verma@example.com",
      "phone": "9876543211",
      "password": "$2b$10$OuhZ6FAE0fgqD3GqjA.oNeOGzjZKmkkNloRiPMuKN863Zltm79Rsu",
      "category": "Sales",
      "position": "Marketing Manager",
      "department": "Marketing",
      "salary": 900000,
      "freeLeavesPerMonth": 2,
      "workingDaysPerWeek": 6,
      "status": "Active",
      "isDeleted": false,
      "salaryHistory": [],
      "dateHired": "2026-02-09T15:20:13.072Z",
      "createdAt": "2026-02-09T15:20:13.073Z",
      "updatedAt": "2026-02-09T15:40:29.824Z",
      "__v": 0
    },
    {
      "_id": "6989fb2de22141062a8df68e",
      "companyId": "69873a5a1d893c740340fcba",
      "firstName": "Amit",
      "lastName": "Patel",
      "email": "amit.patel@example.com-deleted-1770651506087",
      "phone": "9876543212-deleted-1770651506087",
      "password": "$2b$10$l7iyykVIVrJXjAemf9dCWuhNlVAz2TzyJCLyiSQQPKb3KJ2bWlbAu",
      "category": "Sales",
      "position": "Sales Executive",
      "department": "Sales",
      "salary": 600000,
      "freeLeavesPerMonth": 1,
      "workingDaysPerWeek": 6,
      "status": "Terminated",
      "isDeleted": true,
      "salaryHistory": [],
      "dateHired": "2026-02-09T15:20:13.234Z",
      "createdAt": "2026-02-09T15:20:13.235Z",
      "updatedAt": "2026-02-09T15:40:29.969Z",
      "__v": 0
    },
    {
      "_id": "6989fb2de22141062a8df691",
      "companyId": "69873a5a1d893c740340fcba",
      "firstName": "Sneha",
      "lastName": "Reddy",
      "email": "sneha.reddy@example.com-deleted-1770651477989",
      "phone": "9876543213-deleted-1770651477989",
      "password": "$2b$10$sOvQGY9JdbQ0h5N5M08B.eWQNpkc7oPFS4x7FL2So0Ej43KrZ3gqC",
      "category": "Management",
      "position": "HR Specialist",
      "department": "HR",
      "salary": 750000,
      "freeLeavesPerMonth": 1,
      "workingDaysPerWeek": 5,
      "status": "Terminated",
      "isDeleted": true,
      "salaryHistory": [],
      "dateHired": "2026-02-09T15:20:13.379Z",
      "createdAt": "2026-02-09T15:20:13.380Z",
      "updatedAt": "2026-02-09T15:40:30.173Z",
      "__v": 0
    },
    {
      "_id": "6989fb2de22141062a8df694",
      "companyId": "69873a5a1d893c740340fcba",
      "firstName": "Vikram",
      "lastName": "Singh",
      "email": "vikram.singh@example.com-deleted-1770651479976",
      "phone": "9876543214-deleted-1770651479976",
      "password": "$2b$10$k/s5gLuyh5TUrPmvLIynKePSsFzfaCiBf/rTv4MWFaPwpAa4aASHe",
      "category": "General",
      "position": "Support Lead",
      "department": "Customer Support",
      "salary": 500000,
      "freeLeavesPerMonth": 0,
      "workingDaysPerWeek": 6,
      "status": "Terminated",
      "isDeleted": true,
      "salaryHistory": [],
      "dateHired": "2026-02-09T15:20:13.459Z",
      "createdAt": "2026-02-09T15:20:13.460Z",
      "updatedAt": "2026-02-09T15:40:30.357Z",
      "__v": 0
    },
    {
      "_id": "698c9cc72414558cb9002839",
      "companyId": "69873a5a1d893c740340fcba",
      "firstName": "Amit",
      "lastName": "Patel",
      "email": "amit.patel@example.com",
      "phone": "9876543212",
      "password": "password123",
      "category": "Sales",
      "position": "Sales Executive",
      "department": "Sales",
      "salary": 600000,
      "freeLeavesPerMonth": 1,
      "workingDaysPerWeek": 6,
      "status": "Active",
      "isDeleted": false,
      "salaryHistory": [],
      "dateHired": "2026-02-11T15:14:15.132Z",
      "createdAt": "2026-02-11T15:14:15.135Z",
      "updatedAt": "2026-02-11T15:14:15.135Z",
      "__v": 0
    },
    {
      "_id": "698c9cc72414558cb900283c",
      "companyId": "69873a5a1d893c740340fcba",
      "firstName": "Sneha",
      "lastName": "Reddy",
      "email": "sneha.reddy@example.com",
      "phone": "9876543213",
      "password": "password123",
      "category": "Management",
      "position": "HR Specialist",
      "department": "HR",
      "salary": 750000,
      "freeLeavesPerMonth": 1,
      "workingDaysPerWeek": 5,
      "status": "Active",
      "isDeleted": false,
      "salaryHistory": [],
      "dateHired": "2026-02-11T15:14:15.237Z",
      "createdAt": "2026-02-11T15:14:15.238Z",
      "updatedAt": "2026-02-11T15:14:15.238Z",
      "__v": 0
    }
  ],
  "leaves": [
    {
      "_id": "698a0114173d053aaf363c10",
      "companyId": "69873a5a1d893c740340fcba",
      "employeeId": "6989eb9fb58fc7dcd227d18c",
      "type": "Sick Leave",
      "startDate": "2026-03-15T00:00:00.000Z",
      "endDate": "2026-02-19T00:00:00.000Z",
      "reason": "bfgdhfh",
      "status": "Pending",
      "createdAt": "2026-02-09T15:45:24.507Z",
      "updatedAt": "2026-02-09T15:45:24.507Z",
      "__v": 0
    },
    {
      "_id": "698a01f5173d053aaf363c62",
      "companyId": "69873a5a1d893c740340fcba",
      "employeeId": "6989eb9fb58fc7dcd227d18c",
      "type": "Sick Leave",
      "startDate": "2026-02-10T00:00:00.000Z",
      "endDate": "2026-02-10T00:00:00.000Z",
      "reason": "vbgdsxd",
      "status": "Approved",
      "createdAt": "2026-02-09T15:49:09.210Z",
      "updatedAt": "2026-02-09T15:59:13.832Z",
      "__v": 0,
      "adminRemark": ""
    },
    {
      "_id": "698cac5a7f19f439bf00d1d9",
      "companyId": "69873a5a1d893c740340fcba",
      "employeeId": "6989ea8501086ad882a11319",
      "type": "Sick Leave",
      "startDate": "2026-02-12T00:00:00.000Z",
      "endDate": "2026-02-19T00:00:00.000Z",
      "reason": "vcvlnjfnjef",
      "status": "Pending",
      "createdAt": "2026-02-11T16:20:42.049Z",
      "updatedAt": "2026-02-11T16:20:42.049Z",
      "__v": 0
    }
  ]
}